MANIFEST.in
README
setup.py
django_preflight.egg-info/PKG-INFO
django_preflight.egg-info/SOURCES.txt
django_preflight.egg-info/dependency_links.txt
django_preflight.egg-info/requires.txt
django_preflight.egg-info/top_level.txt
preflight/__init__.py
preflight/conf.py
preflight/models.py
preflight/tests.py
preflight/urls.py
preflight/views.py
preflight/management/__init__.py
preflight/management/commands/__init__.py
preflight/management/commands/preflight.py
preflight/templates/preflight/overview.html