Metadata-Version: 1.1
Name: django-preflight
Version: 0.1.5
Summary: Create a page for making sure all settings are correct.
Home-page: https://launchpad.net/django-preflight
Author: Lukasz Czyzykowski
Author-email: lukasz.czyzykowski@canonical.com
License: AGPL-3
Download-URL: https://launchpad.net/django-preflight/+download
Platform: UNKNOWN
Classifier: Development Status :: 5 - Production/Stable
Classifier: Environment :: Web Environment
Classifier: Framework :: Django
Classifier: Intended Audience :: Developers
Classifier: License :: OSI Approved :: GNU Affero General Public License v3
Classifier: Programming Language :: Python
Classifier: Programming Language :: Python :: 2.6
Classifier: Programming Language :: Python :: 2.7
Classifier: Topic :: Internet :: WWW/HTTP :: Site Management
Classifier: Topic :: Software Development :: Quality Assurance
